{
  "templateKey": "ird-resource",
  "date": "2020-11-03T19:47:19.213Z",
  "title": "Cal Hacks",
  "tags": [
    "Competitions"
  ],
  "id": "ba9d6756-916e-49d4-bb7b-ddd895776b13",
  "url": "https://calhacks.io/",
  "description": "The world's largest collegiate hackathon. A nonprofit organization composed of students passionate about fostering a culture of hacking, entrepreneurship, and social good via the empowerment of technology. Their mission is to empower others with technology to create solutions to better the world."
}